[{"i18n":"Internet et hautes technologies","code":"010","children":[{"i18n":"Commerce électronique","code":"01"},{"i18n":"Jeux et divertissements en ligne","code":"02"},{"i18n":"Services en ligne à hors ligne","code":"03"},{"i18n":"Plateforme publicitaire","code":"04"},{"i18n":"Bricolage","code":"05"},{"i18n":"Logiciels et services aux entreprises","code":"06"},{"i18n":"Autres","code":"07"},{"i18n":"On-line Education","code":"08"},{"i18n":"High-tech Manufacturing","code":"09"},{"i18n":"Digital Media","code":"10"}]},{"i18n":"Services professionnels","code":"012","children":[{"i18n":"Informations juridiques","code":"01"},{"i18n":"Comptabilité","code":"02"},{"i18n":"Conseil technique et de gestion","code":"03"},{"i18n":"Recherche et développement scientifique","code":"04"},{"i18n":"Publicité et études de marché","code":"05"},{"i18n":"Autres activités professionnelles","code":"06"}]},{"i18n":"Éducation","code":"014","children":[{"i18n":"Enseignement supérieur","code":"01"},{"i18n":"Enseignement primaire et secondaire","code":"02"},{"i18n":"Enseignement technique et professionnel","code":"03"},{"i18n":"Formation et activités extrascolaires","code":"04"},{"i18n":"Autres du secteur de l'éducation","code":"05"}]},{"i18n":"Arts, divertissement et loisirs ","code":"016","children":[{"i18n":"Actualités et publication","code":"01"},{"i18n":"Créativité, arts et divertissement","code":"02"},{"i18n":"Bibliothèques, archives, musées et autres activités culturelles","code":"03"},{"i18n":"Activités sportives","code":"04"}]},{"i18n":"Technologies de l'information et de la communication","code":"009","children":[{"i18n":"Services de télécommunications","code":"01"},{"i18n":"Radiodiffusion et services par satellite","code":"02"}]},{"i18n":"Vente en gros et au détail","code":"006","children":[{"i18n":"Commerce de gros (à l'exception des véhicules et des motocycles)","code":"01"},{"i18n":"Commerce de détail (à l'exception des véhicules et des motocycles)","code":"02"},{"i18n":"Commerce de gros et de détail et réparation de véhicules et de motocycles","code":"03"}]},{"i18n":"Secteur manufacturier","code":"003","children":[{"i18n":"Informatique, communication et électronique grand public","code":"01"},{"i18n":"Véhicules et équipements de transport","code":"02"},{"i18n":"Nourriture et boissons","code":"03"},{"i18n":"Produits pharmaceutiques","code":"04"},{"i18n":"Consommateur","code":"05"},{"i18n":"Produits chimiques","code":"06"},{"i18n":"Pétrole et gaz naturel","code":"07"},{"i18n":"Textiles et vêtements","code":"08"},{"i18n":"Matériel aérospatial","code":"09"},{"i18n":"Métaux","code":"10"},{"i18n":"Machines et équipements n.c.a.","code":"11"},{"i18n":"Autres secteurs manufacturiers","code":"12"}]},{"i18n":"Finances et assurances","code":"011","children":[{"i18n":"Banque","code":"01"},{"i18n":"Titres, fonds et investissements","code":"02"},{"i18n":"Assurance","code":"03"},{"i18n":"Autres services financiers","code":"04"}]},{"i18n":"Construction et immobilier","code":"005","children":[{"i18n":"Activités immobilières","code":"01"},{"i18n":"Construction de bâtiments et génie civil","code":"02"},{"i18n":"Décoration et autres activités de construction spécialisées","code":"03"}]},{"i18n":"Santé et travail social","code":"015","children":[{"i18n":"Activités liées à la santé humaine ","code":"01"},{"i18n":"Activités de travail social","code":"02"}]},{"i18n":"Crédit-bail et agent","code":"013","children":[{"i18n":"Crédit-bail","code":"01"},{"i18n":"Service d'agent","code":"02"}]},{"i18n":"Services publics, environnement et équipements publics","code":"004","children":[{"i18n":"Services publics","code":"01"},{"i18n":"Activités d'assainissement de l'environnement","code":"02"},{"i18n":"Équipements publics et aménagement du territoire","code":"03"}]},{"i18n":"Hébergement et restauration","code":"008","children":[{"i18n":"Hébergement","code":"01"},{"i18n":"Service de restauration","code":"02"}]},{"i18n":"Transport et logistique","code":"007","children":[{"i18n":"Transport","code":"01"},{"i18n":"Activités d'entreposage, de poste et de coursier","code":"02"}]},{"i18n":"Service public","code":"017","children":[{"i18n":"Gouvernements","code":"01"},{"i18n":"Organisation sociale","code":"02"},{"i18n":"Scientific Institution","code":"03"}]},{"i18n":"Agriculture","code":"001","children":[{"i18n":"Agriculture, sylviculture et pêche","code":"01"},{"i18n":"Autres activités auxiliaires","code":"02"}]},{"i18n":"Organisations extraterritoriales","code":"018"},{"i18n":"Exploitation minière","code":"002","children":[{"i18n":"Charbon, pétrole brut et gaz naturel","code":"01"},{"i18n":"Extraction de minerais","code":"02"},{"i18n":"Activités de service de soutien minier","code":"03"}]},{"i18n":"Autres","code":"019"}]